indic_unified_parser/__init__.py
indic_unified_parser/globals.py
indic_unified_parser/helpers.py
indic_unified_parser/uparser.py
indic_unified_parser/ply/__init__.py
indic_unified_parser/ply/lex.py
indic_unified_parser/ply/yacc.py
indic_unified_parser-1.0.6.dist-info/LICENSE
indic_unified_parser-1.0.6.dist-info/METADATA
indic_unified_parser-1.0.6.dist-info/WHEEL
indic_unified_parser-1.0.6.dist-info/top_level.txt
indic_unified_parser-1.0.6.dist-info/RECORD
