Metadata-Version: 2.1
Name: indic_unified_parser
Version: 1.0.6
Summary: The Unified Parser unifies Indian languages using a common label set and syllable structure. It converts text to a common label set, generates phoneme sequences and improves natural language understanding in Indian languages. The method requires basic language knowledge and can achieve more than 95% accuracy with good lexicons. New Indian language parsers can be easily developed using this unified approach.
Author-email: Vikram K V <vikram.kv2001@gmail.com>
Project-URL: Homepage, https://github.com/vikram-kv/Unified_Parser
Project-URL: Bug Tracker, https://github.com/vikram-kv/Unified_Parser/issues
Classifier: Programming Language :: Python :: 3
Classifier: License :: OSI Approved :: MIT License
Classifier: Operating System :: OS Independent
Requires-Python: >=3.7
License-File: LICENSE
